glizzy_tls/__init__.py
glizzy_tls/exceptions.py
glizzy_tls/models.py
glizzy_tls/request.py
glizzy_tls/session.py
glizzy_tls/dependencies/__init__.py
glizzy_tls/dependencies/build_go.py
glizzy_tls/dependencies/go.mod
glizzy_tls/dependencies/go.sum
glizzy_tls/dependencies/tls_client.go
glizzy_tls-0.1.5.dist-info/LICENSE
glizzy_tls-0.1.5.dist-info/METADATA
glizzy_tls-0.1.5.dist-info/WHEEL
glizzy_tls-0.1.5.dist-info/top_level.txt
glizzy_tls-0.1.5.dist-info/RECORD
