Metadata-Version: 2.1
Name: glizzy_tls
Version: 0.1.5
Summary: A fully open-source, cross-platform TLS implementation in Python, leveraging GoLang.
Home-page: https://github.com/glizzykingdreko/glizzy_tls
Author: glizzykingdreko
Author-email: glizzykingdreko@protonmail.com
License: MIT
Classifier: Development Status :: 3 - Alpha
Classifier: Intended Audience :: Developers
Classifier: Topic :: Software Development :: Build Tools
Classifier: License :: OSI Approved :: MIT License
Classifier: Programming Language :: Python :: 3
Classifier: Programming Language :: Python :: 3.7
Classifier: Programming Language :: Python :: 3.8
Classifier: Programming Language :: Python :: 3.9
Requires-Python: >=3.7
License-File: LICENSE
